registry_du/__init__.py
registry_du/registry_du.py
registry_du-0.0.2.dist-info/METADATA
registry_du-0.0.2.dist-info/WHEEL
registry_du-0.0.2.dist-info/entry_points.txt
registry_du-0.0.2.dist-info/top_level.txt
registry_du-0.0.2.dist-info/RECORD
