Metadata-Version: 2.1
Name: registry-du
Version: 0.0.2
Summary: Give you a better view of your Docker registry disk usage.
Home-page: https://github.com/n0vad3v/registry-du
Author: Nova Kwok
Author-email: noc@nova.moe
License: UNKNOWN
Platform: UNKNOWN
Classifier: Programming Language :: Python :: 3
Classifier: License :: OSI Approved :: GNU General Public License v3 (GPLv3)
Classifier: Operating System :: OS Independent
Requires-Dist: terminaltables
